MANIFEST.in
README
setup.py
bubble/__init__.py
bubble/frozen.py
bubble/bclient/__init__.py
bubble/bclient/connector.py
bubble/bclient/tools.py
bubble/bclient/wabout.py
bubble/bclient/wbubblec.py
bubble/bclient/wdark.py
bubble/bclient/wmask.py
bubble/bclient/wplot.py
bubble/bclient/wsaxsparams.py
bubble/bclient/wsopts.py
bubble/bclient/ui/__init__.py
bubble/bclient/ui/resources_rc.py
bubble/bclient/ui/ui_wabout.py
bubble/bclient/ui/ui_wsopts.py
bubble/bclient/ui/wbubble.py
bubble/bclient/ui/wdark.py
bubble/bclient/ui/wmask.py
bubble/bclient/ui/wsaxsparams.py
bubble/bcommon/__init__.py
bubble/bcommon/compressor.py
bubble/bcommon/default.py
bubble/bserver/__init__.py
bubble/bserver/config.py
bubble/bserver/integrator.py
bubble/bserver/interface.py
bubble/bserver/server.py
bubble/bserver/watcher.py
bubble/bserver/worker.py
bubble_dubble.egg-info/PKG-INFO
bubble_dubble.egg-info/SOURCES.txt
bubble_dubble.egg-info/dependency_links.txt
bubble_dubble.egg-info/entry_points.txt
bubble_dubble.egg-info/requires.txt
bubble_dubble.egg-info/top_level.txt