Metadata-Version: 1.0
Name: bubble-dubble
Version: 2018.11.28
Summary: Azimuthal powder integration
Home-page: https://hg.3lp.cx/bubble
Author: Vadim Dyadkin
Author-email: dyadkin@gmail.com
License: GPLv3
Platform: UNKNOWN
